{
  "info": {
    "_postman_id": "1e1e7a90-0002-4000-9000-collection-000000000001",
    "name": "Backend API",
    "schema": "https://schema.getpostman.com/json/collection/v2.1.0/collection.json",
    "description": "Colección de endpoints del Backend API"
  },
  "item": [
    {
      "name": "Auth",
      "item": [
        {
          "name": "Login",
          "request": {
            "method": "POST",
            "header": [
              { "key": "Content-Type", "value": "application/json" }
            ],
            "url": { "raw": "{{baseUrl}}/api/v1/auth/login", "host": ["{{baseUrl}}"], "path": ["api","v1","auth","login"] },
            "body": {
              "mode": "raw",
              "raw": "{\n  \"email\": \"{{email}}\",\n  \"password\": \"{{password}}\"\n}"
            }
          },
          "event": [
            {
              "listen": "test",
              "script": {
                "type": "text/javascript",
                "exec": [
                  "// Parse JSON and basic checks",
                  "pm.test('Status code is 200', function () { pm.response.to.have.status(200); });",
                  "pm.test('Response time < 1500ms', function () { pm.expect(pm.response.responseTime).to.be.below(1500); });",
                  "pm.test('Body has token', function () { const json = pm.response.json(); pm.expect(json).to.have.property('token'); pm.expect(json.token).to.be.a('string').that.is.not.empty; });",
                  "// Save token to environment",
                  "const json = pm.response.json(); pm.environment.set('token', json.token);"
                ]
              }
            }
          ]
        },
        {
          "name": "Forgot Password",
          "request": {
            "method": "POST",
            "header": [ { "key": "Content-Type", "value": "application/json" } ],
            "url": { "raw": "{{baseUrl}}/api/v1/auth/forgot-password", "host": ["{{baseUrl}}"], "path": ["api","v1","auth","forgot-password"] },
            "body": { "mode": "raw", "raw": "{\n  \"email\": \"{{email}}\"\n}" }
          },
          "event": [
            {"listen":"test","script":{"type":"text/javascript","exec":[
              "pm.test('Status code is 200', function () { pm.response.to.have.status(200); });",
              "pm.test('Has message', function () { const json = pm.response.json(); pm.expect(json).to.have.property('message'); });"
            ]}}
          ]
        },
        {
          "name": "Reset Password",
          "request": {
            "method": "POST",
            "header": [ { "key": "Content-Type", "value": "application/json" } ],
            "url": { "raw": "{{baseUrl}}/api/v1/auth/reset-password", "host": ["{{baseUrl}}"], "path": ["api","v1","auth","reset-password"] },
            "body": { "mode": "raw", "raw": "{\n  \"email\": \"{{email}}\",\n  \"newPassword\": \"NewPassw0rd!\",\n  \"otp\": \"123456\"\n}" }
          },
          "event": [
            {"listen":"test","script":{"type":"text/javascript","exec":[
              "pm.test('Status code is 200', function () { pm.response.to.have.status(200); });",
              "pm.test('Has message', function () { const json = pm.response.json(); pm.expect(json).to.have.property('message'); });"
            ]}}
          ]
        }
      ]
    },
    {
      "name": "Users",
      "item": [
        {
          "name": "Create User",
          "request": {
            "method": "POST",
            "header": [ { "key": "Content-Type", "value": "application/json" } ],
            "url": { "raw": "{{baseUrl}}/api/v1/users", "host": ["{{baseUrl}}"], "path": ["api","v1","users"] },
            "body": { "mode": "raw", "raw": "{\n  \"identification\": \"{{identification}}\",\n  \"username\": \"demo.user\",\n  \"name\": \"Demo\",\n  \"lastnameone\": \"User\",\n  \"lastnametwo\": \"Test\",\n  \"borndate\": \"2000-01-01\",\n  \"email\": \"{{email}}\",\n  \"phone\": \"+56999999999\",\n  \"password\": \"{{password}}\",\n  \"idusertype\": 1,\n  \"idtypeident\": 1\n}" }
          },
          "event": [
            {"listen":"test","script":{"type":"text/javascript","exec":[
              "pm.test('Status code is 200', function () { pm.response.to.have.status(200); });",
              "pm.test('Has message', function () { const json = pm.response.json(); pm.expect(json).to.have.property('message'); });"
            ]}}
          ]
        },
        {
          "name": "Get User",
          "request": {
            "method": "GET",
            "header": [ {"key":"Authorization","value":"Bearer {{token}}"} ],
            "url": { "raw": "{{baseUrl}}/api/v1/users/{{identification}}", "host": ["{{baseUrl}}"], "path": ["api","v1","users","{{identification}}"] }
          },
          "event": [
            {"listen":"test","script":{"type":"text/javascript","exec":[
              "pm.test('Status code is 200 or 401', function () { pm.expect([200,401]).to.include(pm.response.code); });",
              "if (pm.response.code === 200) { const json = pm.response.json(); pm.test('Has user in body', function () { pm.expect(json).to.have.property('user'); }); }"
            ]}}
          ]
        },
        {
          "name": "Update User",
          "request": {
            "method": "PUT",
            "header": [ {"key":"Authorization","value":"Bearer {{token}}"}, { "key": "Content-Type", "value": "application/json" } ],
            "url": { "raw": "{{baseUrl}}/api/v1/users/{{identification}}", "host": ["{{baseUrl}}"], "path": ["api","v1","users","{{identification}}"] },
            "body": { "mode": "raw", "raw": "{\n  \"identification\": \"{{identification}}\",\n  \"username\": \"demo.user.updated\"\n}" }
          },
          "event": [
            {"listen":"test","script":{"type":"text/javascript","exec":[
              "pm.test('Status code is 200', function () { pm.response.to.have.status(200); });",
              "pm.test('Has message', function () { const json = pm.response.json(); pm.expect(json).to.have.property('message'); });"
            ]}}
          ]
        },
        {
          "name": "Delete User",
          "request": {
            "method": "DELETE",
            "header": [ {"key":"Authorization","value":"Bearer {{token}}"} ],
            "url": { "raw": "{{baseUrl}}/api/v1/users/{{identification}}", "host": ["{{baseUrl}}"], "path": ["api","v1","users","{{identification}}"] }
          },
          "event": [
            {"listen":"test","script":{"type":"text/javascript","exec":[
              "pm.test('Status is 200 or 404', function () { pm.expect([200,404,401]).to.include(pm.response.code); });"
            ]}}
          ]
        }
      ]
    },
    {
      "name": "Accounts",
      "item": [
        {
          "name": "Create Account",
          "request": {
            "method": "POST",
            "header": [ {"key":"Content-Type","value":"application/json"} ],
            "url": { "raw": "{{baseUrl}}/api/v1/accounts", "host": ["{{baseUrl}}"], "path": ["api","v1","accounts"] },
            "body": { "mode": "raw", "raw": "{\n  \"iban\": \"ES7620770024003102575766\",\n  \"funds\": 5000,\n  \"iduser\": \"{{identification}}\",\n  \"idtypemoney\": \"EUR\",\n  \"idtypeaccount\": \"CHK\"\n}" }
          },
          "event": [ {"listen":"test","script":{"type":"text/javascript","exec":[
            "pm.test('Status code is 200', function () { pm.response.to.have.status(200); });"
          ]}} ]
        },
        {
          "name": "See Account",
          "request": {
            "method": "GET",
            "header": [ {"key":"Authorization","value":"Bearer {{token}}"} ],
            "url": { "raw": "{{baseUrl}}/api/v1/accounts/{{accountId}}", "host": ["{{baseUrl}}"], "path": ["api","v1","accounts","{{accountId}}"] }
          },
          "event": [ {"listen":"test","script":{"type":"text/javascript","exec":[
            "pm.test('Status 200 or 404 or 401', function () { pm.expect([200,404,401]).to.include(pm.response.code); });"
          ]}} ]
        },
        {
          "name": "See Accounts",
          "request": {
            "method": "GET",
            "header": [ {"key":"Authorization","value":"Bearer {{token}}"} ],
            "url": { "raw": "{{baseUrl}}/api/v1/accounts/{{identification}}", "host": ["{{baseUrl}}"], "path": ["api","v1","accounts","{{identification}}"] }
          },
          "event": [ {"listen":"test","script":{"type":"text/javascript","exec":[
            "pm.test('Status 200 or 401', function () { pm.expect([200,401]).to.include(pm.response.code); });"
          ]}} ]
        },
        {
          "name": "Account Movements",
          "request": {
            "method": "GET",
            "header": [ {"key":"Authorization","value":"Bearer {{token}}"} ],
            "url": { "raw": "{{baseUrl}}/api/v1/accounts/{{accountId}}/movements", "host": ["{{baseUrl}}"], "path": ["api","v1","accounts","{{accountId}}","movements"] }
          },
          "event": [ {"listen":"test","script":{"type":"text/javascript","exec":[
            "pm.test('Status 200 or 401', function () { pm.expect([200,401]).to.include(pm.response.code); });"
          ]}} ]
        },
        {
          "name": "Set Account Status",
          "request": {
            "method": "POST",
            "header": [ {"key":"Authorization","value":"Bearer {{token}}"}, {"key":"Content-Type","value":"application/json"} ],
            "url": { "raw": "{{baseUrl}}/api/v1/accounts/{{accountId}}/status", "host": ["{{baseUrl}}"], "path": ["api","v1","accounts","{{accountId}}","status"] },
            "body": { "mode": "raw", "raw": "{\n  \"status\": \"active\"\n}" }
          },
          "event": [ {"listen":"test","script":{"type":"text/javascript","exec":[
            "pm.test('Status 200 or 401', function () { pm.expect([200,401]).to.include(pm.response.code); });"
          ]}} ]
        }
      ]
    },
    {
      "name": "Cards",
      "item": [
        {
          "name": "Create Card",
          "request": {"method":"POST","header":[{"key":"Authorization","value":"Bearer {{token}}"},{"key":"Content-Type","value":"application/json"}],
            "url": {"raw":"{{baseUrl}}/api/v1/cards","host":["{{baseUrl}}"],"path":["api","v1","cards"]},
            "body":{"mode":"raw","raw":"{\n  \"numbercard\": \"{{cardId}}\",\n  \"iban\": \"{{accountId}}\",\n  \"iduser\": \"{{identification}}\",\n  \"pin\": \"1234\",\n  \"cvv\": \"999\",\n  \"expdate\": \"2028-12-31\"\n}"}
          },
          "event":[{"listen":"test","script":{"type":"text/javascript","exec":[
            "pm.test('Status 200 or 401', function () { pm.expect([200,401]).to.include(pm.response.code); });"
          ]}}]
        },
        {
          "name": "Get Card",
          "request": {"method":"GET","header":[{"key":"Authorization","value":"Bearer {{token}}"}],
            "url":{"raw":"{{baseUrl}}/api/v1/cards/{{cardId}}","host":["{{baseUrl}}"],"path":["api","v1","cards","{{cardId}}"]}
          },
          "event":[{"listen":"test","script":{"type":"text/javascript","exec":[
            "pm.test('Status 200 or 404 or 401', function () { pm.expect([200,404,401]).to.include(pm.response.code); });"
          ]}}]
        },
        {
          "name": "Get Card Movements",
          "request": {"method":"GET","header":[{"key":"Authorization","value":"Bearer {{token}}"}],
            "url":{"raw":"{{baseUrl}}/api/v1/cards/{{cardId}}/movements","host":["{{baseUrl}}"],"path":["api","v1","cards","{{cardId}}","movements"]}
          },
          "event":[{"listen":"test","script":{"type":"text/javascript","exec":[
            "pm.test('Status 200 or 401', function () { pm.expect([200,401]).to.include(pm.response.code); });"
          ]}}]
        },
        {
          "name": "Get Cards by Identification",
          "request": {"method":"GET","header":[{"key":"Authorization","value":"Bearer {{token}}"}],
            "url":{"raw":"{{baseUrl}}/api/v1/cards?identification={{identification}}","host":["{{baseUrl}}"],"path":["api","v1","cards"],"query":[{"key":"identification","value":"{{identification}}"}]}
          },
          "event":[{"listen":"test","script":{"type":"text/javascript","exec":[
            "pm.test('Status 200 or 401', function () { pm.expect([200,401]).to.include(pm.response.code); });"
          ]}}]
        }
      ]
    },
    {
      "name": "PIN/CVV",
      "item": [
        {
          "name": "Generate OTP PIN/CVV",
          "request": {"method":"POST","header":[{"key":"Authorization","value":"Bearer {{token}}"}],
            "url":{"raw":"{{baseUrl}}/api/v1/cards/{{cardId}}/otp","host":["{{baseUrl}}"],"path":["api","v1","cards","{{cardId}}","otp"]}
          },
          "event":[{"listen":"test","script":{"type":"text/javascript","exec":[
            "pm.test('Status 200 or 401', function () { pm.expect([200,401]).to.include(pm.response.code); });"
          ]}}]
        },
        {
          "name": "View details with OTP",
          "request": {"method":"POST","header":[{"key":"Authorization","value":"Bearer {{token}}"},{"key":"Content-Type","value":"application/json"}],
            "url":{"raw":"{{baseUrl}}/api/v1/cards/{{cardId}}/view-details","host":["{{baseUrl}}"],"path":["api","v1","cards","{{cardId}}","view-details"]},
            "body":{"mode":"raw","raw":"{\n  \"otp\": \"123456\",\n  \"cardID\": \"{{cardId}}\"\n}"}
          },
          "event":[{"listen":"test","script":{"type":"text/javascript","exec":[
            "pm.test('Status 200 or 401', function () { pm.expect([200,401]).to.include(pm.response.code); });"
          ]}}]
        }
      ]
    },
    {
      "name": "Transfers",
      "item": [
        {
          "name": "Internal Transfer",
          "request": {"method":"POST","header":[{"key":"Authorization","value":"Bearer {{token}}"},{"key":"Content-Type","value":"application/json"}],
            "url":{"raw":"{{baseUrl}}/api/v1/transfers/internal","host":["{{baseUrl}}"],"path":["api","v1","transfers","internal"]},
            "body":{"mode":"raw","raw":"{\n  \"from\": \"{{accountId}}\",\n  \"to\": \"{{accountId}}\",\n  \"amount\": 10.5,\n  \"details\": \"Pago prueba\"\n}"}
          },
          "event":[{"listen":"test","script":{"type":"text/javascript","exec":[
            "pm.test('Status 200 or 401', function () { pm.expect([200,401]).to.include(pm.response.code); });"
          ]}}]
        }
      ]
    },
    {
      "name": "Validate Accounts",
      "item": [
        {
          "name": "Validate Account",
          "request": {"method":"POST","header":[{"key":"Authorization","value":"Bearer {{token}}"},{"key":"Content-Type","value":"application/json"}],
            "url":{"raw":"{{baseUrl}}/api/v1/accounts/validate","host":["{{baseUrl}}"],"path":["api","v1","accounts","validate"]},
            "body":{"mode":"raw","raw":"{\n  \"accountNumber\": \"{{accountId}}\",\n  \"bankCode\": \"999\"\n}"}
          },
          "event":[{"listen":"test","script":{"type":"text/javascript","exec":[
            "pm.test('Status 200 or 401', function () { pm.expect([200,401]).to.include(pm.response.code); });",
            "if (pm.response.code === 200) { const json = pm.response.json(); pm.test('Has data.isValid', function () { pm.expect(json).to.have.nested.property('data.isValid'); }); }"
          ]}}]
        }
      ]
    }
  ],
  "event": [
    {
      "listen": "prerequest",
      "script": {
        "id": "prerequest-collection",
        "exec": [
          "// Set a run id for trace",
          "pm.collectionVariables.set('runId', pm.collectionVariables.get('runId') || pm.variables.replaceIn('{{$guid}}'));"
        ],
        "type": "text/javascript"
      }
    },
    {
      "listen": "test",
      "script": {
        "id": "test-collection",
        "exec": [
          "// Ensure JSON responses when possible",
          "pm.test('Response content-type is JSON when body present', function () { const ct = pm.response.headers.get('Content-Type') || ''; if (pm.response.text()) { pm.expect(ct.toLowerCase()).to.include('application/json'); } });"
        ],
        "type": "text/javascript"
      }
    }
  ],
  "variable": [
    {"key":"runId","value":""}
  ]
}